google_colab_mcp-1.0.1.dist-info/licenses/LICENSE
mcp_colab_server/__init__.py
mcp_colab_server/auth_manager.py
mcp_colab_server/chrome_profile_manager.py
mcp_colab_server/colab_drive.py
mcp_colab_server/colab_selenium.py
mcp_colab_server/config_manager.py
mcp_colab_server/diagnostics.py
mcp_colab_server/server.py
mcp_colab_server/session_manager.py
mcp_colab_server/setup.py
mcp_colab_server/utils.py
mcp_colab_server/templates/credentials_template.json
mcp_colab_server/templates/server_config.json
google_colab_mcp-1.0.1.dist-info/METADATA
google_colab_mcp-1.0.1.dist-info/WHEEL
google_colab_mcp-1.0.1.dist-info/entry_points.txt
google_colab_mcp-1.0.1.dist-info/top_level.txt
google_colab_mcp-1.0.1.dist-info/RECORD
