Metadata-Version: 2.4
Name: google-colab-mcp
Version: 1.0.1
Summary: Model Context Protocol server for seamless Google Colab integration with AI assistants
Author: inkbytefo
Author-email: inkbytefo <inkbytefo@gmail.com>
License-Expression: MIT
Project-URL: Homepage, https://github.com/inkbytefo/google-colab-mcp
Project-URL: Documentation, https://github.com/inkbytefo/google-colab-mcp#readme
Project-URL: Repository, https://github.com/inkbytefo/google-colab-mcp.git
Project-URL: Bug Tracker, https://github.com/inkbytefo/google-colab-mcp/issues
Keywords: mcp,google-colab,ai,assistant,jupyter,notebook,automation
Classifier: Development Status :: 4 - Beta
Classifier: Intended Audience :: Developers
Classifier: Intended Audience :: Science/Research
Classifier: Operating System :: OS Independent
Classifier: Programming Language :: Python :: 3
Classifier: Programming Language :: Python :: 3.8
Classifier: Programming Language :: Python :: 3.9
Classifier: Programming Language :: Python :: 3.10
Classifier: Programming Language :: Python :: 3.11
Classifier: Programming Language :: Python :: 3.12
Classifier: Topic :: Scientific/Engineering :: Artificial Intelligence
Classifier: Topic :: Software Development :: Libraries :: Python Modules
Classifier: Topic :: Internet :: WWW/HTTP :: Browsers
Requires-Python: >=3.8
License-File: LICENSE
Requires-Dist: google-auth>=2.0.0
Requires-Dist: google-auth-oauthlib>=0.5.0
Requires-Dist: google-auth-httplib2>=0.1.0
Requires-Dist: google-api-python-client>=2.0.0
Requires-Dist: selenium>=4.0.0
Requires-Dist: webdriver-manager>=3.8.0
Requires-Dist: mcp>=1.0.0
Requires-Dist: pydantic>=2.0.0
Requires-Dist: requests>=2.25.0
Provides-Extra: dev
Requires-Dist: pytest>=7.0.0; extra == "dev"
Requires-Dist: pytest-asyncio>=0.21.0; extra == "dev"
Requires-Dist: black>=22.0.0; extra == "dev"
Requires-Dist: flake8>=4.0.0; extra == "dev"
Requires-Dist: mypy>=1.0.0; extra == "dev"
Requires-Dist: build>=0.8.0; extra == "dev"
Requires-Dist: twine>=4.0.0; extra == "dev"
Dynamic: author
Dynamic: license-file
Dynamic: requires-python
